codeify/__init__.py
codeify/__main__.py
codeify/codegen.py
codeify/conversions.py
codeify/modules.py
codeify/template.py
codeify/text.py
codeify/types.py
codeify-0.3.3.dist-info/METADATA
codeify-0.3.3.dist-info/WHEEL
codeify-0.3.3.dist-info/entry_points.txt
codeify-0.3.3.dist-info/top_level.txt
codeify-0.3.3.dist-info/RECORD
