Metadata-Version: 2.1
Name: codeify
Version: 0.3.3
Summary: Python-based development utilities
Home-page: https://www.nuradius.com
Author: Nuradius Software
Author-email: todd@datacomponents.net
License: Apache Software License
Classifier: Development Status :: 3 - Alpha
Classifier: Intended Audience :: Developers
Classifier: License :: OSI Approved :: Apache Software License
Classifier: Programming Language :: Python
Classifier: Programming Language :: Python :: 3
Classifier: Programming Language :: Python :: 3.7
Classifier: Programming Language :: Python :: 3.8
Classifier: Programming Language :: Python :: 3.9
Classifier: Programming Language :: Python :: 3.10
Classifier: Programming Language :: Python :: 3.11
Classifier: Programming Language :: Python :: 3.12
Requires-Python: >=3.7
Requires-Dist: Jinja2 ==3.1.2
Requires-Dist: PyYAML ==6.0.1
